pysparkrpc/__init__.py
pysparkrpc/api_client.py
pysparkrpc/proxy.py
pysparkrpc/server/__init__.py
pysparkrpc/server/capture.py
pysparkrpc/server/cli.py
pysparkrpc/server/logger.py
pysparkrpc/server/server.py
pysparkrpc-0.6.0.dist-info/entry_points.txt
pysparkrpc-0.6.0.dist-info/LICENSE
pysparkrpc-0.6.0.dist-info/WHEEL
pysparkrpc-0.6.0.dist-info/METADATA
pysparkrpc-0.6.0.dist-info/RECORD
